README.md
heroku_kafka_eze.py
setup.cfg
setup.py
heroku_kafka_eze.egg-info/PKG-INFO
heroku_kafka_eze.egg-info/SOURCES.txt
heroku_kafka_eze.egg-info/dependency_links.txt
heroku_kafka_eze.egg-info/requires.txt
heroku_kafka_eze.egg-info/top_level.txt