Metadata-Version: 1.1
Name: heroku-kafka-eze
Version: 0.0.1
Summary: Python kafka package for use with heroku's kafka. You'll only need your heroku api key
Home-page: https://github.com/masalomon01/heroku-kafka-eze
Author: MarSal
Author-email: salermom@gmail.com
License: MIT
Keywords: heroku,kafka
Platform: UNKNOWN
Classifier: Development Status :: 5 - Production/Stable
Classifier: License :: OSI Approved :: MIT License
Classifier: Programming Language :: Python :: 2.7
Classifier: Programming Language :: Python :: 3
Classifier: Intended Audience :: Developers
